dsprg/__init__.py
dsprg/data.txt
dsprg/dsprg.py
dsprg/main.py
dsprg-1.0.3.dist-info/LICENSE
dsprg-1.0.3.dist-info/METADATA
dsprg-1.0.3.dist-info/WHEEL
dsprg-1.0.3.dist-info/top_level.txt
dsprg-1.0.3.dist-info/RECORD
