Metadata-Version: 2.1
Name: dsprg
Version: 1.0.3
Summary: A package for nothing
Author: petteer1
Classifier: Programming Language :: Python :: 3
Classifier: License :: OSI Approved :: MIT License
Classifier: Operating System :: OS Independent
License-File: LICENSE
